tulpa/__init__.py
tulpa/py.typed
tulpa-0.1.0.dist-info/METADATA
tulpa-0.1.0.dist-info/WHEEL
tulpa-0.1.0.dist-info/licenses/LICENSE
tulpa-0.1.0.dist-info/RECORD
