Metadata-Version: 2.4
Name: tulpa
Version: 0.1.0
Summary: Tools enabling generative AI to interact with the physical world
Project-URL: Homepage, https://github.com/phillipdupuis/tulpa
Project-URL: Repository, https://github.com/phillipdupuis/tulpa
Author-email: Phillip Dupuis <phillip_dupuis@alumni.brown.edu>
License: GNU General Public License v3.0
License-File: LICENSE
Requires-Python: >=3.9
Provides-Extra: dev
Requires-Dist: coverage; extra == 'dev'
Requires-Dist: pytest; extra == 'dev'
Requires-Dist: pytest-cov; extra == 'dev'
Requires-Dist: ruff; extra == 'dev'
